hugsim_client/__init__.py
hugsim_client/client.py
hugsim_client-0.0.8.dist-info/METADATA
hugsim_client-0.0.8.dist-info/WHEEL
hugsim_client-0.0.8.dist-info/RECORD
