Metadata-Version: 2.4
Name: hugsim_client
Version: 0.0.8
Summary: A client package for interacting with the HugSim API.
Project-URL: homepage, https://github.com/longxiaofei/HUGSIM/tree/hf-competitions/client
Project-URL: repository, https://github.com/longxiaofei/HUGSIM/tree/hf-competitions/client
Author: XDimLab
License-Expression: MIT
Requires-Python: >=3.7
Requires-Dist: numpy
Requires-Dist: requests
Requires-Dist: tenacity
